leximpact_dotations_back/__init__.py
leximpact_dotations_back/computing/__init__.py
leximpact_dotations_back/computing/calculate.py
leximpact_dotations_back/computing/calculate_impact.py
leximpact_dotations_back/computing/calculate_impact_commune.py
leximpact_dotations_back/computing/calculate_impact_strates.py
leximpact_dotations_back/computing/calculate_impact_total.py
leximpact_dotations_back/computing/compare.py
leximpact_dotations_back/computing/dotations_simulation.py
leximpact_dotations_back/computing/reform.py
leximpact_dotations_back/computing/reform_plf_2026_variables.py
leximpact_dotations_back/computing/simulation_2024.py
leximpact_dotations_back/computing/simulation_common.py
leximpact_dotations_back/computing/strate_demographique.py
leximpact_dotations_back/configure_logging.py
leximpact_dotations_back/data_building/__init__.py
leximpact_dotations_back/data_building/adapt_dotations_criteres.py
leximpact_dotations_back/data_building/build_dotations_data.py
leximpact_dotations_back/dotations_types.py
leximpact_dotations_back/load_configuration.py
leximpact_dotations_back/main.py
leximpact_dotations_back/main_types.py
leximpact_dotations_back/mapping/__init__.py
leximpact_dotations_back/mapping/criteres_dgcl_2023.py
leximpact_dotations_back/mapping/criteres_dgcl_2024.py
leximpact_dotations_back/mapping/criteres_dgcl_2025.py
leximpact_dotations_back/mapping/parameters.py
leximpact_dotations_back/mapping/reform_parameters.py
leximpact_dotations_back/mapping/valeurs_dgcl.py
leximpact_dotations_back/preload.py
leximpact_dotations_back-6.0.0.dist-info/METADATA
leximpact_dotations_back-6.0.0.dist-info/WHEEL
leximpact_dotations_back-6.0.0.dist-info/licenses/LICENSE
leximpact_dotations_back-6.0.0.dist-info/RECORD
