Metadata-Version: 2.4
Name: leximpact-dotations-back
Version: 6.0.0
Summary: Simulating annual State grants to the French administrative divisions
License: AGPL-3.0-or-later
License-File: LICENSE
Author: LexImpact
Author-email: leximpact@assemblee-nationale.fr
Requires-Python: >=3.9,<3.12
Classifier: Development Status :: 3 - Alpha
Classifier: Intended Audience :: Developers
Classifier: Intended Audience :: Legal Industry
Classifier: Intended Audience :: Other Audience
Classifier: Intended Audience :: Science/Research
Classifier: License :: OSI Approved :: GNU Affero General Public License v3 or later (AGPLv3+)
Classifier: Programming Language :: Python
Classifier: Programming Language :: Python :: 3
Classifier: Programming Language :: Python :: 3.9
Classifier: Programming Language :: Python :: 3.10
Classifier: Programming Language :: Python :: 3.11
Requires-Dist: fastapi[standard] (>=0.117.0,<0.118.0)
Requires-Dist: openfisca-france-dotations-locales (>=4.0.0,<5.0.0)
Requires-Dist: pandas (>=2.2.2,<3.0.0)
Requires-Dist: python-dotenv (>=1.1.1,<2.0.0)
Project-URL: Repository, https://git.leximpact.dev/leximpact/simulateur-dotations-communes/leximpact-dotations-back
